pal/__init__.py
pal/config.py
pal/contracts.py
pal/copulas.py
pal/couplings.py
pal/distributions.py
pal/frequency_severity.py
pal/py.typed
pal/reserve_risk.py
pal/stats.py
pal/stochastic_scalar.py
pal/variables.py
pcm/__init__.py
pcm/catastrophes.py
pcm/config.py
pcm/contracts.py
pcm/copulas.py
pcm/couplings.py
pcm/distributions.py
pcm/frequency_severity.py
pcm/reserve_risk.py
pcm/stats.py
pcm/stochastic_scalar.py
pcm/variables.py
proteus_actuarial_library-0.0.10.dist-info/licenses/LICENSE
proteus_actuarial_library-0.0.10.dist-info/METADATA
proteus_actuarial_library-0.0.10.dist-info/WHEEL
proteus_actuarial_library-0.0.10.dist-info/top_level.txt
proteus_actuarial_library-0.0.10.dist-info/RECORD
