Metadata-Version: 2.4
Name: proteus-actuarial-library
Version: 0.0.10
Summary: Proteus Actuarial Library: A package for building and running stochastic actuarial models in Python.
Author-email: James Norman <james.norman@proteusllp.com>
License: MIT License with Commons Clause
Project-URL: Homepage, https://github.com/pythactuary/python-capital-model
Project-URL: Issues, https://github.com/pythactuary/python-capital-model/issues
Keywords: actuarial,insurance,capital
Classifier: Programming Language :: Python :: 3
Classifier: License :: Other/Proprietary License
Classifier: Operating System :: OS Independent
Requires-Python: >=3.11
License-File: LICENSE
Requires-Dist: numpy
Requires-Dist: scipy
Requires-Dist: plotly
Provides-Extra: gpu
Requires-Dist: cupy-cuda12x; extra == "gpu"
Dynamic: license-file
